odoo/addons/barcodes_generator_lot/README.rst
odoo/addons/barcodes_generator_lot/__init__.py
odoo/addons/barcodes_generator_lot/__manifest__.py
odoo/addons/barcodes_generator_lot/demo/barcode_rule.xml
odoo/addons/barcodes_generator_lot/demo/function.xml
odoo/addons/barcodes_generator_lot/demo/ir_sequence.xml
odoo/addons/barcodes_generator_lot/demo/stock_production_lot.xml
odoo/addons/barcodes_generator_lot/i18n/barcodes_generator_lot.pot
odoo/addons/barcodes_generator_lot/i18n/es.po
odoo/addons/barcodes_generator_lot/i18n/es_ES.po
odoo/addons/barcodes_generator_lot/i18n/fr.po
odoo/addons/barcodes_generator_lot/i18n/hr.po
odoo/addons/barcodes_generator_lot/i18n/nl_NL.po
odoo/addons/barcodes_generator_lot/models/__init__.py
odoo/addons/barcodes_generator_lot/models/barcode_rule.py
odoo/addons/barcodes_generator_lot/models/stock_production_lot.py
odoo/addons/barcodes_generator_lot/static/description/icon.png
odoo/addons/barcodes_generator_lot/static/description/icon.svg
odoo/addons/barcodes_generator_lot/static/description/stock_production_lot_sequence_generation.png
odoo/addons/barcodes_generator_lot/tests/__init__.py
odoo/addons/barcodes_generator_lot/tests/test_barcode_generator.py
odoo/addons/barcodes_generator_lot/views/stock_production_lot.xml
odoo11_addon_barcodes_generator_lot-11.0.1.0.0.99.dev1.dist-info/METADATA
odoo11_addon_barcodes_generator_lot-11.0.1.0.0.99.dev1.dist-info/RECORD
odoo11_addon_barcodes_generator_lot-11.0.1.0.0.99.dev1.dist-info/WHEEL
odoo11_addon_barcodes_generator_lot-11.0.1.0.0.99.dev1.dist-info/top_level.txt
